README.txt
setup.py
contemarlo/Distribution.py
contemarlo/Resolver.py
contemarlo/__init__.py
contemarlo.egg-info/PKG-INFO
contemarlo.egg-info/SOURCES.txt
contemarlo.egg-info/dependency_links.txt
contemarlo.egg-info/top_level.txt