Metadata-Version: 1.1
Name: contemarlo
Version: 1.0.0
Summary: Deterministic Monte-Carlo-Like without memory constraints.
Home-page: http://rbirm.us
Author: Ryan Birmingham
Author-email: birm@rbirm.us
License: UNKNOWN
Platform: UNKNOWN
Classifier: Development Status :: 2 - Pre-Alpha
Classifier: Topic :: Scientific/Engineering :: Mathematics
Classifier: License :: OSI Approved :: GNU General Public License (GPL)
